osmium/__init__.py
osmium/_osmium.cpython-314-aarch64-linux-gnu.so
osmium/_osmium.pyi
osmium/area.cpython-314-aarch64-linux-gnu.so
osmium/area.pyi
osmium/back_reference_writer.py
osmium/file_processor.py
osmium/filter.cpython-314-aarch64-linux-gnu.so
osmium/filter.pyi
osmium/forward_reference_writer.py
osmium/geom.cpython-314-aarch64-linux-gnu.so
osmium/geom.pyi
osmium/helper.py
osmium/index.cpython-314-aarch64-linux-gnu.so
osmium/index.pyi
osmium/io.cpython-314-aarch64-linux-gnu.so
osmium/io.pyi
osmium/py.typed
osmium/simple_handler.py
osmium/version.py
osmium/version.pyi
osmium/osm/__init__.py
osmium/osm/_osm.cpython-314-aarch64-linux-gnu.so
osmium/osm/_osm.pyi
osmium/osm/mutable.py
osmium/osm/types.py
osmium/replication/__init__.py
osmium/replication/_replication.cpython-314-aarch64-linux-gnu.so
osmium/replication/_replication.pyi
osmium/replication/server.py
osmium/replication/utils.py
osmium/tools/__init__.py
osmium/tools/pyosmium_get_changes.py
osmium/tools/pyosmium_up_to_date.py
osmium.libs/libbz2-549b318a.so.1.0.6
osmium.libs/liblz4-b2322fcc.so.1.8.3
osmium-4.1.0.dist-info/METADATA
osmium-4.1.0.dist-info/WHEEL
osmium-4.1.0.dist-info/entry_points.txt
osmium-4.1.0.dist-info/RECORD
osmium-4.1.0.dist-info/licenses/LICENSE.TXT
