Metadata-Version: 2.1
Name: osmium
Version: 4.1.0
Summary: Python bindings for libosmium, the data processing library for OSM data
Keywords: OSM,OpenStreetMap,Osmium
Author-Email: Sarah Hoffmann <lonvia@denofr.de>
Maintainer-Email: Sarah Hoffmann <lonvia@denofr.de>
License: BSD-2-Clause
Classifier: Development Status :: 5 - Production/Stable
Classifier: Intended Audience :: Developers
Classifier: Topic :: Scientific/Engineering :: GIS
Classifier: License :: OSI Approved :: BSD License
Classifier: Programming Language :: Python :: 3.8
Classifier: Programming Language :: Python :: 3.9
Classifier: Programming Language :: Python :: 3.10
Classifier: Programming Language :: Python :: 3.11
Classifier: Programming Language :: Python :: 3.12
Classifier: Programming Language :: Python :: 3.13
Classifier: Programming Language :: Python :: 3.14
Classifier: Programming Language :: Python :: Free Threading :: 2 - Beta
Classifier: Programming Language :: Python :: Implementation :: CPython
Classifier: Programming Language :: C++
Classifier: Typing :: Typed
Requires-Python: >=3.8
Requires-Dist: requests
Provides-Extra: tests
Requires-Dist: pytest; extra == "tests"
Requires-Dist: pytest-httpserver; extra == "tests"
Requires-Dist: pytest-run-parallel; extra == "tests"
Requires-Dist: werkzeug; extra == "tests"
Requires-Dist: shapely; extra == "tests"
Provides-Extra: docs
Requires-Dist: mkdocs; extra == "docs"
Requires-Dist: mkdocs-material; extra == "docs"
Requires-Dist: mkdocstrings; extra == "docs"
Requires-Dist: mkdocstrings-python; extra == "docs"
Requires-Dist: mkdocs-autorefs; extra == "docs"
Requires-Dist: mkdocs-gen-files; extra == "docs"
Requires-Dist: mkdocs-jupyter; extra == "docs"
Requires-Dist: argparse-manpage; extra == "docs"
